boax/__init__.py
boax/version.py
boax/core/__init__.py
boax/core/distributions/__init__.py
boax/core/distributions/beta.py
boax/core/distributions/gamma.py
boax/core/distributions/multivariate_normal.py
boax/core/distributions/normal.py
boax/core/distributions/poisson.py
boax/core/distributions/transformed.py
boax/core/distributions/uniform.py
boax/core/samplers/__init__.py
boax/core/samplers/alias.py
boax/core/samplers/base.py
boax/core/samplers/functions/__init__.py
boax/core/samplers/functions/iid.py
boax/core/samplers/functions/quasi_random.py
boax/core/samplers/functions/utils.py
boax/optimization/__init__.py
boax/optimization/acquisitions/__init__.py
boax/optimization/acquisitions/alias.py
boax/optimization/acquisitions/base.py
boax/optimization/acquisitions/transformed.py
boax/optimization/acquisitions/constraints/__init__.py
boax/optimization/acquisitions/constraints/alias.py
boax/optimization/acquisitions/constraints/base.py
boax/optimization/acquisitions/functions/__init__.py
boax/optimization/acquisitions/functions/analytic.py
boax/optimization/acquisitions/functions/monte_carlo.py
boax/optimization/optimizers/__init__.py
boax/optimization/optimizers/alias.py
boax/optimization/optimizers/base.py
boax/optimization/optimizers/initializers/__init__.py
boax/optimization/optimizers/initializers/alias.py
boax/optimization/optimizers/initializers/base.py
boax/optimization/optimizers/solvers/__init__.py
boax/optimization/optimizers/solvers/alias.py
boax/optimization/optimizers/solvers/base.py
boax/optimization/policies/__init__.py
boax/optimization/policies/alias.py
boax/optimization/policies/base.py
boax/optimization/policies/evaluators/__init__.py
boax/optimization/policies/evaluators/alias.py
boax/optimization/policies/evaluators/base.py
boax/prediction/__init__.py
boax/prediction/models/__init__.py
boax/prediction/models/base.py
boax/prediction/models/gaussian_process.py
boax/prediction/models/transformed.py
boax/prediction/models/functions/__init__.py
boax-0.1.3.dist-info/LICENSE
boax-0.1.3.dist-info/METADATA
boax-0.1.3.dist-info/WHEEL
boax-0.1.3.dist-info/top_level.txt
boax-0.1.3.dist-info/RECORD
