Metadata-Version: 2.1
Name: boax
Version: 0.1.3
Summary: Boax is a Bayesian Optimization library for JAX.
Project-URL: homepage, https://github.com/Lando-L/boax
Classifier: Development Status :: 3 - Alpha
Classifier: Intended Audience :: Developers
Classifier: Intended Audience :: Science/Research
Classifier: License :: OSI Approved :: Apache Software License
Classifier: Programming Language :: Python :: 3.11
Classifier: Programming Language :: Python :: 3.12
Classifier: Topic :: Scientific/Engineering :: Artificial Intelligence
Requires-Python: >=3.11
License-File: LICENSE
Requires-Dist: numpy >=1.26.2
Requires-Dist: jax >=0.4.20
Requires-Dist: jaxlib >=0.4.20
Requires-Dist: chex >=0.1.84
Provides-Extra: docs
Requires-Dist: ipython >=8.18.1 ; extra == 'docs'
Requires-Dist: matplotlib >=3.8.2 ; extra == 'docs'
Requires-Dist: myst-nb >=1.0.0 ; extra == 'docs'
Requires-Dist: optax >=0.1.7 ; extra == 'docs'
Requires-Dist: sphinx >=6.2.1 ; extra == 'docs'
Requires-Dist: sphinx-autodoc-typehints >=1.23.0 ; extra == 'docs'
Requires-Dist: sphinx-book-theme >=1.1.2 ; extra == 'docs'
Provides-Extra: tests
Requires-Dist: absl-py >=2.0.0 ; extra == 'tests'
Requires-Dist: pytest >=7.4.3 ; extra == 'tests'
Requires-Dist: pytest-cov >=4.1.0 ; extra == 'tests'
